alumath/__init__.py
alumath/matrix.py
alumathpeer11-1.0.0.dist-info/licenses/LICENSE.md
alumathpeer11-1.0.0.dist-info/METADATA
alumathpeer11-1.0.0.dist-info/WHEEL
alumathpeer11-1.0.0.dist-info/top_level.txt
alumathpeer11-1.0.0.dist-info/RECORD
