Metadata-Version: 2.4
Name: alumathpeer11
Version: 1.0.0
Summary: Pure Python matrix operations library without external dependencies
Home-page: https://github.com/Mugisha-isaac/ALU_Formatie_2
Author: alumathpeer11 Team
Author-email: i.mugisha@alustudent.com
Keywords: matrix,multiplication,linear algebra,mathematics
Classifier: Development Status :: 4 - Beta
Classifier: Intended Audience :: Developers
Classifier: License :: OSI Approved :: MIT License
Classifier: Operating System :: OS Independent
Classifier: Programming Language :: Python :: 3
Classifier: Programming Language :: Python :: 3.7
Classifier: Programming Language :: Python :: 3.8
Classifier: Programming Language :: Python :: 3.9
Classifier: Programming Language :: Python :: 3.10
Classifier: Programming Language :: Python :: 3.11
Requires-Python: >=3.7
License-File: LICENSE.md
Dynamic: author
Dynamic: author-email
Dynamic: classifier
Dynamic: description
Dynamic: description-content-type
Dynamic: home-page
Dynamic: keywords
Dynamic: license-file
Dynamic: requires-python
Dynamic: summary
